devialet/__init__.py
devialet/const.py
devialet/devialet_api.py
devialet-1.5.6.dist-info/LICENSE
devialet-1.5.6.dist-info/METADATA
devialet-1.5.6.dist-info/WHEEL
devialet-1.5.6.dist-info/top_level.txt
devialet-1.5.6.dist-info/RECORD
